isCubed/__init__.py
isCubed-0.1.dist-info/LICENSE
isCubed-0.1.dist-info/METADATA
isCubed-0.1.dist-info/WHEEL
isCubed-0.1.dist-info/top_level.txt
isCubed-0.1.dist-info/RECORD
