Metadata-Version: 2.1
Name: isCubed
Version: 0.1
Summary: Check if number is perfect cube
Home-page: https://github.com/MiTo0o
Author: MiTo
Author-email: derzanchiang1800@gmail.com
License: MIT
Platform: UNKNOWN
